{
  "centroids": [
    [
      {
        "centroid": {
          "x": 1379,
          "y": 735
        },
        "cell_coordinates": {
          "x": 0,
          "y": 0
        },
        "trust": 1
      },
      {
        "centroid": {
          "x": 573,
          "y": 726
        },
        "cell_coordinates": {
          "x": -20,
          "y": 0
        },
        "trust": 1
      },
      {
        "centroid": {
          "x": 1367,
          "y": 1431
        },
        "cell_coordinates": {
          "x": 0,
          "y": -10
        },
        "trust": 1
      },
      {
        "centroid": {
          "x": 967,
          "y": 1432
        },
        "cell_coordinates": {
          "x": -10,
          "y": -10
        },
        "trust": 1
      },
      {
        "centroid": {
          "x": 765,
          "y": 1078
        },
        "cell_coordinates": {
          "x": -15,
          "y": -5
        },
        "trust": 1
      },
      {
        "centroid": {
          "x": 1413,
          "y": 1084
        },
        "cell_coordinates": {
          "x": 1,
          "y": -5
        },
        "trust": 1
      }
    ],
    [
      {
        "centroid": {
          "x": 630,
          "y": 730
        },
        "cell_coordinates": {
          "x": 0,
          "y": 0
        },
        "trust": 1
      },
      {
        "centroid": {
          "x": 1435,
          "y": 738
        },
        "cell_coordinates": {
          "x": 20,
          "y": 0
        },
        "trust": 1
      },
      {
        "centroid": {
          "x": 1027,
          "y": 1434
        },
        "cell_coordinates": {
          "x": 10,
          "y": -10
        },
        "trust": 1
      },
      {
        "centroid": {
          "x": 627,
          "y": 1427
        },
        "cell_coordinates": {
          "x": 0,
          "y": -10
        },
        "trust": 1
      },
      {
        "centroid": {
          "x": 1234,
          "y": 1086
        },
        "cell_coordinates": {
          "x": 15,
          "y": -5
        },
        "trust": 1
      },
      {
        "centroid": {
          "x": 586,
          "y": 1080
        },
        "cell_coordinates": {
          "x": -1,
          "y": -5
        },
        "trust": 1
      },
      {
        "centroid": {
          "x": 1033,
          "y": 732
        },
        "cell_coordinates": {
          "x": 10,
          "y": 0
        },
        "trust": 1
      }
    ],
    [
      {
        "centroid": {
          "x": 1387,
          "y": 1375
        },
        "cell_coordinates": {
          "x": 0,
          "y": 0
        },
        "trust": 1
      },
      {
        "centroid": {
          "x": 588,
          "y": 1369
        },
        "cell_coordinates": {
          "x": -20,
          "y": 0
        },
        "trust": 1
      },
      {
        "centroid": {
          "x": 991,
          "y": 671
        },
        "cell_coordinates": {
          "x": -10,
          "y": 10
        },
        "trust": 1
      },
      {
        "centroid": {
          "x": 1394,
          "y": 675
        },
        "cell_coordinates": {
          "x": 0,
          "y": 10
        },
        "trust": 1
      },
      {
        "centroid": {
          "x": 784,
          "y": 1023
        },
        "cell_coordinates": {
          "x": -15,
          "y": 5
        },
        "trust": 1
      },
      {
        "centroid": {
          "x": 1435,
          "y": 1026
        },
        "cell_coordinates": {
          "x": 1,
          "y": 5
        },
        "trust": 1
      }
    ],
    [
      {
        "centroid": {
          "x": 627,
          "y": 1385
        },
        "cell_coordinates": {
          "x": 0,
          "y": 0
        },
        "trust": 1
      },
      {
        "centroid": {
          "x": 1422,
          "y": 1388
        },
        "cell_coordinates": {
          "x": 20,
          "y": 0
        },
        "trust": 1
      },
      {
        "centroid": {
          "x": 629,
          "y": 690
        },
        "cell_coordinates": {
          "x": 0,
          "y": 10
        },
        "trust": 1
      },
      {
        "centroid": {
          "x": 1030,
          "y": 690
        },
        "cell_coordinates": {
          "x": 10,
          "y": 10
        },
        "trust": 1
      },
      {
        "centroid": {
          "x": 1231,
          "y": 1044
        },
        "cell_coordinates": {
          "x": 15,
          "y": 5
        },
        "trust": 1
      },
      {
        "centroid": {
          "x": 584,
          "y": 1040
        },
        "cell_coordinates": {
          "x": -1,
          "y": 5
        },
        "trust": 1
      }
    ]
  ],
  "order": [
    [
      2,
      3
    ],
    [
      0,
      1
    ]
  ]
}

